scatter_append/__init__.py
scatter_append/scatter_append.py
scatter_append-0.4.dist-info/METADATA
scatter_append-0.4.dist-info/WHEEL
scatter_append-0.4.dist-info/top_level.txt
scatter_append-0.4.dist-info/RECORD
