Metadata-Version: 2.4
Name: scatter-append
Version: 0.4
Summary: A utility for scatter appending to mutable sequences.
Author-email: Rhys Newbury <rhys.newbury@monash.edu>, Bryce Ferenczi <bryce.ferenczi@monash.edu>
License: MIT
Project-URL: Homepage, https://github.com/rhys-newbury/ScatterAppend
Classifier: Programming Language :: Python :: 3
Classifier: License :: OSI Approved :: MIT License
Classifier: Operating System :: OS Independent
Requires-Python: >=3.6
